expli/__init__.py
expli/main.py
expli/main.pyi
expli/py.typed
expli-0.0.4.dist-info/licenses/LICENSE
expli-0.0.4.dist-info/METADATA
expli-0.0.4.dist-info/WHEEL
expli-0.0.4.dist-info/top_level.txt
expli-0.0.4.dist-info/RECORD
