Metadata-Version: 2.4
Name: expli
Version: 0.0.4
Summary: Enhanced dataclasses with automatic dict/JSON serialization for nested structures
Author: Daniel Olson
Author-email: daniel@orphos.cloud
Keywords: dataclass,serialization,json,dict,nested,typing,dataclasses,decorator,deserialization
Classifier: Development Status :: 3 - Alpha
Classifier: Intended Audience :: Developers
Classifier: License :: OSI Approved :: MIT License
Classifier: Operating System :: OS Independent
Classifier: Programming Language :: Python :: 3
Classifier: Programming Language :: Python :: 3.10
Classifier: Programming Language :: Python :: 3.11
Classifier: Programming Language :: Python :: 3.12
Requires-Python: >=3.10
License-File: LICENSE
Requires-Dist: typing_extensions>=4.0.0; python_version < "3.11"
Dynamic: author
Dynamic: author-email
Dynamic: classifier
Dynamic: description
Dynamic: description-content-type
Dynamic: keywords
Dynamic: license-file
Dynamic: requires-dist
Dynamic: requires-python
Dynamic: summary
